setup.py
quaidan/__init__.py
quaidan/client.py
quaidan/command.py
quaidan/status.py
quaidan.egg-info/PKG-INFO
quaidan.egg-info/SOURCES.txt
quaidan.egg-info/dependency_links.txt
quaidan.egg-info/requires.txt
quaidan.egg-info/top_level.txt
tests/__init__.py
tests/client_test.py
tests/command_test.py
tests/status_test.py