Metadata-Version: 1.1
Name: quaidan
Version: 0.2.1
Summary: Quaidan is a python wrapper for mod_proxy_balancer's balancer manager.
Home-page: http://github.com/stefanbirkner/quaidan/
Author: Stefan Birkner
Author-email: mail@stefan-birkner.de
License: MIT License
Download-URL: https://github.com/stefanbirkner/quaidan/archive/quaidan-0.2.1.tar.gz
Platform: any
Classifier: Development Status :: 4 - Beta
Classifier: Environment :: Console
Classifier: Intended Audience :: System Administrators
Classifier: License :: OSI Approved :: MIT License
Classifier: Natural Language :: English
Classifier: Operating System :: OS Independent
Classifier: Programming Language :: Python
Classifier: Topic :: Internet :: WWW/HTTP :: HTTP Servers
Classifier: Topic :: Software Development :: Libraries :: Python Modules
Classifier: Topic :: System :: Systems Administration
